Workbook
Name TotalMonthlyExpenses: 'FEBRERO 26'!$F$8
Name TotalMonthlyExpenses: 'ENERO 26'!$F$8
Name TotalMonthlyIncome: 'FEBRERO 26'!$F$5
Name TotalMonthlyIncome: 'ENERO 26'!$F$5
Name TotalMonthlySavings: 'FEBRERO 26'!$F$11
Name TotalMonthlySavings: 'ENERO 26'!$F$11
Name TotalMonthlyExpenses: 'MARZO 26'!$F$8
Name TotalMonthlyIncome: 'MARZO 26'!$F$5
Name TotalMonthlySavings: 'MARZO 26'!$F$11
Name TotalMonthlyExpenses: 'ABRIL 26'!$F$9
Name TotalMonthlyIncome: 'ABRIL 26'!$F$6
Name TotalMonthlySavings: 'ABRIL 26'!$F$12
Name TotalMonthlyExpenses: 'MAYO 26'!$F$9
Name TotalMonthlyIncome: 'MAYO 26'!$F$6
Name TotalMonthlySavings: 'MAYO 26'!$F$12
Name TotalMonthlyExpenses: 'JUNIO 26'!$F$9
Name TotalMonthlyIncome: 'JUNIO 26'!$F$6
Name TotalMonthlySavings: 'JUNIO 26'!$F$12
Name TotalMonthlyExpenses: 'JULIO 26'!$F$9
Name TotalMonthlyIncome: 'JULIO 26'!$F$6
Name TotalMonthlySavings: 'JULIO 26'!$F$12
Name TotalMonthlyExpenses: 'SEPTIEMBRE 26'!$F$9
Name TotalMonthlyIncome: 'SEPTIEMBRE 26'!$F$6
Name TotalMonthlySavings: 'SEPTIEMBRE 26'!$F$12
Name TotalMonthlyExpenses: 'AGOSTO 26'!$F$9
Name TotalMonthlyIncome: 'AGOSTO 26'!$F$6
Name TotalMonthlySavings: 'AGOSTO 26'!$F$12
Name TotalMonthlyExpenses: 'OCTUBRE 26'!$F$9
Name TotalMonthlyIncome: 'OCTUBRE 26'!$F$6
Name TotalMonthlySavings: 'OCTUBRE 26'!$F$12
Name TotalMonthlyExpenses: 'NOVIEMBRE 26'!$F$9
Name TotalMonthlyIncome: 'NOVIEMBRE 26'!$F$6
Name TotalMonthlySavings: 'NOVIEMBRE 26'!$F$12
Name TotalMonthlyExpenses: 'DICIEMBRE 26'!$F$9
Name TotalMonthlyIncome: 'DICIEMBRE 26'!$F$6
Name TotalMonthlySavings: 'DICIEMBRE 26'!$F$12

Sheet DICIEMBRE 26
A1: Volver al directorio
B2: Presupuesto personal
B3: Porcentaje de ingresos gastados | F3: Resumen
F4: TOTAL INGRESOS MENSUALES
F6: =SUM(MonthlyIncome7_41013172023293235[CANTIDAD]) -> 0
F7: TOTAL GASTOS MENSUALES
F9: =SUM(MonthlyExpenses8_51114161922283136[CANTIDAD]) -> 0
F10: TOTAL AHORROS MENSUALES
F12: ='DICIEMBRE 26'!TotalMonthlyIncome-'DICIEMBRE 26'!TotalMonthlyExpenses -> 0
F13: SALDO DE CUENTA
F15: =SUM('NOVIEMBRE 26'!F15+'DICIEMBRE 26'!TotalMonthlySavings) -> 1243.07
B16: INGRESOS DICIEMBRE | E16: GASTOS DICIEMBRE | I16: Ahorros mensuales
B17: ARTÍCULO | C17: CANTIDAD | E17: ARTÍCULO | F17: CANTIDAD | H17: AHORRO ANUAL | J17: GASTO ANUAL | M17: INGRESO ANUAL
B18: Ingreso Irene | E18: Alquiler | H18: =SUM('ENERO 26'!F11,'FEBRERO 26'!F11,'MARZO 26'!F11,'ABRIL 26'!F12,'MAYO 26'!F12,'JUNIO 26'!F12,'JULIO 26'!F12,'AGOSTO 26'!F12,'SEPTIEMBRE 26'!F12,'OCTUBRE 26'!F12,'NOVIEMBRE 26'!F12,F12) -> -188.93 | J18: =SUM('ENERO 26'!F8,'FEBRERO 26'!F8,'MARZO 26'!F8,'ABRIL 26'!F9,'MAYO 26'!F9,'JUNIO 26'!F9,'JULIO 26'!F9,'AGOSTO 26'!F9,'SEPTIEMBRE 26'!F9,'OCTUBRE 26'!F9,'NOVIEMBRE 26'!F9,F9) -> 2688.93 | M18: =SUM('ENERO 26'!F5,'FEBRERO 26'!F5,'MARZO 26'!F5,'ABRIL 26'!F6,'MAYO 26'!F6,'JUNIO 26'!F6,'JULIO 26'!F6,'AGOSTO 26'!F6,'SEPTIEMBRE 26'!F6,'OCTUBRE 26'!F6,'NOVIEMBRE 26'!F6,F6) -> 2500
B19: Ingreso Diego | E19: Ocio
E20: Compra Mercadona
E21: IKEA
E22: Aerotermia
E23: Compra Primor
E24: Compra Ahorramás
E25: DIGI
E26: Compra Lidl
E27: Compra Carrefour
E28: Compra Alcampo

Sheet NOVIEMBRE 26
A1: Volver al directorio
B2: Presupuesto personal
B3: Porcentaje de ingresos gastados | F3: Resumen
F4: TOTAL INGRESOS MENSUALES
F6: =SUM(MonthlyIncome7_410131720232932[CANTIDAD]) -> 0
F7: TOTAL GASTOS MENSUALES
F9: =SUM(MonthlyExpenses8_511141619222831[CANTIDAD]) -> 0
F10: TOTAL AHORROS MENSUALES
F12: ='NOVIEMBRE 26'!TotalMonthlyIncome-'NOVIEMBRE 26'!TotalMonthlyExpenses -> 0
F13: SALDO DE CUENTA
F15: =SUM('OCTUBRE 26'!F15+'NOVIEMBRE 26'!TotalMonthlySavings) -> 1243.07
B16: INGRESOS NOVIEMBRE | E16: GASTOS NOVIEMBRE | I16: Ahorros mensuales
B17: ARTÍCULO | C17: CANTIDAD | E17: ARTÍCULO | F17: CANTIDAD | H17: FECHA | I17: CANTIDAD
B18: Ingreso Irene | E18: Alquiler
B19: Ingreso Diego | E19: Compra Mercadona
E20: Compra Carrefour
E21: IKEA
E22: Iberdrola
E23: Agua
E24: Aerotermia
E25: Ocio
E26: DIGI
E27: Octopus

Sheet OCTUBRE 26
A1: Volver al directorio
B2: Presupuesto personal
B3: Porcentaje de ingresos gastados | F3: Resumen
F4: TOTAL INGRESOS MENSUALES
F6: =SUM(MonthlyIncome7_4101317202329[CANTIDAD]) -> 0
F7: TOTAL GASTOS MENSUALES
F9: =SUM(MonthlyExpenses8_5111416192228[CANTIDAD]) -> 0
F10: TOTAL AHORROS MENSUALES
F12: ='OCTUBRE 26'!TotalMonthlyIncome-'OCTUBRE 26'!TotalMonthlyExpenses -> 0
F13: SALDO DE CUENTA
F15: =SUM('SEPTIEMBRE 26'!F15+'OCTUBRE 26'!TotalMonthlySavings) -> 1243.07
B16: INGRESOS OCTUBRE | E16: GASTOS OCTUBRE | I16: Ahorros mensuales
B17: ARTÍCULO | C17: CANTIDAD | E17: ARTÍCULO | F17: CANTIDAD | H17: FECHA | I17: CANTIDAD
B18: Ingreso Irene | E18: Alquiler
B19: Ingreso Diego | E19: Compra Mercadona
E20: Leroy Merlin
E21: Compra Carrefour
E22: Gasolina
E23: Iberdrola
E24: IKEA
E25: Ocio
E26: Aerotermia
E27: DIGI

Sheet SEPTIEMBRE 26
A1: Volver al directorio
B2: Presupuesto personal
B3: Porcentaje de ingresos gastados | F3: Resumen
F4: TOTAL INGRESOS MENSUALES
F6: =SUM(MonthlyIncome7_41013172023[CANTIDAD]) -> 0
F7: TOTAL GASTOS MENSUALES
F9: =SUM(MonthlyExpenses8_51114161922[CANTIDAD]) -> 0
F10: TOTAL AHORROS MENSUALES
F12: ='SEPTIEMBRE 26'!TotalMonthlyIncome-'SEPTIEMBRE 26'!TotalMonthlyExpenses -> 0
F13: SALDO DE CUENTA
F15: =SUM('AGOSTO 26'!F15+'SEPTIEMBRE 26'!TotalMonthlySavings) -> 1243.07
B16: INGRESOS SEPTIEMBRE | E16: GASTOS SEPTIEMBRE | I16: Ahorros mensuales
B17: ARTÍCULO | C17: CANTIDAD | E17: ARTÍCULO | F17: CANTIDAD | H17: FECHA | I17: CANTIDAD
B18: Ingreso Irene | E18: Alquiler
B19: Ingreso Diego | E19: Aerotermia
E20: Compra Mercadona
E21: Pescadería
E22: Iberdrola
E23: Agua
E24: DIGI
E25: Bocadillo
E26: IKEA

Sheet AGOSTO 26
A1: Volver al directorio
B2: Presupuesto personal
B3: Porcentaje de ingresos gastados | F3: Resumen
F4: TOTAL INGRESOS MENSUALES
F6: =SUM(MonthlyIncome7_4101317202326[CANTIDAD]) -> 0
F7: TOTAL GASTOS MENSUALES
F9: =SUM(MonthlyExpenses8_5111416192225[CANTIDAD]) -> 0
F10: TOTAL AHORROS MENSUALES
F12: ='AGOSTO 26'!TotalMonthlyIncome-'AGOSTO 26'!TotalMonthlyExpenses -> 0
F13: SALDO DE CUENTA
F15: =SUM('JULIO 26'!F15+'AGOSTO 26'!TotalMonthlySavings) -> 1243.07
B16: INGRESOS AGOSTO | E16: GASTOS AGOSTO | I16: Ahorros mensuales
B17: ARTÍCULO | C17: CANTIDAD | E17: ARTÍCULO | F17: CANTIDAD | H17: FECHA | I17: CANTIDAD
B18: Ingreso Irene | E18: Alquiler
B19: Ingreso Diego | E19: Compra Mercadona
E20: Compra Carrefour
E21: Iberdrola
E22: Compras varias
E23: Aerotermia
E24: DIGI

Sheet JULIO 26
A1: Volver al directorio
B2: Presupuesto personal
B3: Porcentaje de ingresos gastados | F3: Resumen
F4: TOTAL INGRESOS MENSUALES
F6: =SUM(MonthlyIncome7_410131720[CANTIDAD]) -> 0
F7: TOTAL GASTOS MENSUALES
F9: =SUM(MonthlyExpenses8_511141619[CANTIDAD]) -> 0
F10: TOTAL AHORROS MENSUALES
F12: ='JULIO 26'!TotalMonthlyIncome-'JULIO 26'!TotalMonthlyExpenses -> 0
F13: SALDO DE CUENTA
F15: =SUM('JUNIO 26'!F15+'JULIO 26'!TotalMonthlySavings) -> 1243.07
B16: INGRESOS JULIO | E16: GASTOS JULIO | I16: Ahorros mensuales
B17: ARTÍCULO | C17: CANTIDAD | E17: ARTÍCULO | F17: CANTIDAD | H17: FECHA | I17: CANTIDAD
B18: Ingreso Irene | E18: Alquiler
B19: Ingreso Diego | E19: Compra Carrefour
E20: Compra Mercadona
E21: Decoración
E22: Iberdrola
E23: Agua
E24: Compra Alcampo
E25: Aerotermia
E26: Kebap
E27: Frutería
E28: DIGI

Sheet JUNIO 26
A1: Volver al directorio
B2: Presupuesto personal
B3: Porcentaje de ingresos gastados | F3: Resumen
F4: TOTAL INGRESOS MENSUALES
F6: =SUM(MonthlyIncome7_4101317[CANTIDAD]) -> 0
F7: TOTAL GASTOS MENSUALES
F9: =SUM(MonthlyExpenses8_5111416[CANTIDAD]) -> 0
F10: TOTAL AHORROS MENSUALES
F12: ='JUNIO 26'!TotalMonthlyIncome-'JUNIO 26'!TotalMonthlyExpenses -> 0
F13: SALDO DE CUENTA
F15: =SUM('MAYO 26'!F15+'JUNIO 26'!TotalMonthlySavings) -> 1243.07
B16: INGRESOS JUNIO | E16: GASTOS JUNIO | I16: Ahorros mensuales
B17: ARTÍCULO | C17: CANTIDAD | E17: ARTÍCULO | F17: CANTIDAD | H17: FECHA | I17: CANTIDAD
B18: Ingreso Irene | E18: Alquiler
B19: Ingreso Diego | E19: Compra Mercadona
B20: Devolución IKEA | E20: Muebles y decoración
E21: Iberdrola
E22: Salmón IKEA
E23: Aerotermia
E24: McDonald's
E25: DIGI
E26: Frutería

Sheet MAYO 26
A1: Volver al directorio
B2: Presupuesto personal
B3: Porcentaje de ingresos gastados | F3: Resumen
F4: TOTAL INGRESOS MENSUALES
F6: =SUM(MonthlyIncome7_41013[CANTIDAD]) -> 0
F7: TOTAL GASTOS MENSUALES
F9: =SUM(MonthlyExpenses8_51114[CANTIDAD]) -> 0
F10: TOTAL AHORROS MENSUALES
F12: ='MAYO 26'!TotalMonthlyIncome-'MAYO 26'!TotalMonthlyExpenses -> 0
F13: SALDO DE CUENTA
F15: =SUM('ABRIL 26'!F15+'MAYO 26'!TotalMonthlySavings) -> 1243.07
B16: INGRESOS MAYO | E16: GASTOS MAYO | I16: Ahorros mensuales
B17: ARTÍCULO | C17: CANTIDAD | E17: ARTÍCULO | F17: CANTIDAD | H17: FECHA | I17: CANTIDAD
B18: Ingreso Irene | E18: Alquiler
B19: Ingreso Diego | E19: Compra Mercadona
E20: Muebles y decoración
E21: Compra Carrefour
E22: Iberdrola
E23: Compra Lidl
E24: Agua
E25: Aerotermia
E26: DIGI

Sheet ABRIL 26
A1: Volver al directorio
B2: Presupuesto personal
B3: Porcentaje de ingresos gastados | F3: Resumen
F4: TOTAL INGRESOS MENSUALES
F6: =SUM(MonthlyIncome7_410[CANTIDAD]) -> 0
F7: TOTAL GASTOS MENSUALES
F9: =SUM(MonthlyExpenses8_511[CANTIDAD]) -> 0
F10: TOTAL AHORROS MENSUALES
F12: ='ABRIL 26'!TotalMonthlyIncome-'ABRIL 26'!TotalMonthlyExpenses -> 0
F13: SALDO DE CUENTA
F15: =SUM('MARZO 26'!F14+'ABRIL 26'!TotalMonthlySavings) -> 1243.07
B16: INGRESOS ABRIL | E16: GASTOS ABRIL | I16: Ahorros mensuales
B17: ARTÍCULO | C17: CANTIDAD | E17: ARTÍCULO | F17: CANTIDAD | H17: FECHA | I17: CANTIDAD
B18: Ingreso Irene | E18: Alquiler
B19: Ingreso Diego | E19: Compra Mercadona
E20: Muebles y decoración
E21: Compra Carrefour
E22: Seguro del hogar
E23: Iberdrola
E24: Aerotermia
E25: Mando garaje
E26: DIGI

Sheet MARZO 26
B1: Presupuesto personal
B2: Porcentaje de ingresos gastados | F2: Resumen
F3: TOTAL INGRESOS MENSUALES
F5: =SUM(MonthlyIncome7_4[CANTIDAD]) -> 0
F6: TOTAL GASTOS MENSUALES
F8: =SUM(MonthlyExpenses8_5[CANTIDAD]) -> 0
F9: TOTAL AHORROS MENSUALES
F11: ='MARZO 26'!TotalMonthlyIncome-'MARZO 26'!TotalMonthlyExpenses -> 0
F12: SALDO DE CUENTA
F14: =SUM('FEBRERO 26'!F14+'MARZO 26'!TotalMonthlySavings) -> 1243.07
B15: INGRESOS MARZO | E15: GASTOS MARZO | I15: Ahorros mensuales
B16: ARTÍCULO | C16: CANTIDAD | E16: ARTÍCULO | F16: CANTIDAD | H16: FECHA | I16: CANTIDAD
B17: Ingreso Irene | E17: Alquiler
B18: Ingreso Diego | E18: Muebles y decoración
E19: Compra Mercadona
E20: Compra Alcampo
E21: Compra Carrefour
E22: Aerotermia
E23: Iberdrola
E24: Agua
E25: DIGI

Sheet FEBRERO 26
B1: Presupuesto personal
B2: Porcentaje de ingresos gastados | F2: Resumen
F3: TOTAL INGRESOS MENSUALES
F5: =SUM(MonthlyIncome7[CANTIDAD]) -> 1250
F6: TOTAL GASTOS MENSUALES
F8: =SUM(MonthlyExpenses8[CANTIDAD]) -> 1353.54
F9: TOTAL AHORROS MENSUALES
F11: ='FEBRERO 26'!TotalMonthlyIncome-'FEBRERO 26'!TotalMonthlyExpenses -> -103.54
F12: SALDO DE CUENTA
F14: =SUM('ENERO 26'!F14+'FEBRERO 26'!TotalMonthlySavings) -> 1243.07
B15: INGRESOS FEBRERO | E15: GASTOS FEBRERO | I15: Ahorros mensuales
B16: ARTÍCULO | C16: CANTIDAD | E16: ARTÍCULO | F16: CANTIDAD | H16: FECHA | I16: CANTIDAD
B17: Ingreso Irene | C17: 750 | E17: Alquiler | F17: 771.98
B18: Ingreso Diego | C18: 500 | E18: Compra Mercadona | F18: 181.92
E19: Compra Carrefour | F19: 112.63
E20: Muebles IKEA | F20: 96
E21: Aerotermia | F21: 68.68
E22: Octopus Energy | F22: 42.12
E23: Compra Lidl | F23: 40.97
E24: Fruta | F24: 15.25
E25: Compra Alcampo | F25: 13.99
E26: DIGI | F26: 10

Sheet ENERO 26
B1: Presupuesto personal
B2: Porcentaje de ingresos gastados | F2: Resumen
F3: TOTAL INGRESOS MENSUALES
F5: =SUM(MonthlyIncome[CANTIDAD]) -> 1250
F6: TOTAL GASTOS MENSUALES
F8: =SUM(MonthlyExpenses[CANTIDAD]) -> 1335.39
F9: TOTAL AHORROS MENSUALES
F11: =F5-F8 -> -85.39
F12: SALDO DE CUENTA
F14: =SUM(I16+TotalMonthlySavings) -> 1346.61
B15: INGRESOS ENERO | E15: GASTOS ENERO | I15: SALDO CUENTA
B16: ARTÍCULO | C16: CANTIDAD | E16: ARTÍCULO | F16: CANTIDAD | I16: 1432
B17: Ingreso Irene | C17: 750 | E17: Alquiler | F17: 771.98
B18: Ingreso Diego | C18: 500 | E18: Compra Mercadona | F18: 202.26
E19: Compra Carrefour | F19: 170.4
E20: Muebles | F20: 50
E21: Aerotermia | F21: 48.07
E22: Agua | F22: 33.35
E23: Octopus | F23: 19.21
E24: Ocio | F24: 16.18
E25: Compra Alcampo | F25: 13.94
E26: DIGI | F26: 10

Sheet Datos del gráfico
A1: Volver al directorio
B2: DATOS DEL GRÁFICO
B4: =MIN(1-B5,1) -> 0
B5: =MIN(TotalMonthlyExpenses/TotalMonthlyIncome,1) -> 1
B6: =(TotalMonthlyExpenses/TotalMonthlyIncome)>1 -> TRUE
